diseloryaHelper/__init__.py
diseloryaHelper/chineseLanguageHelper.py
diseloryaHelper/ocrHelper.py
diseloryaHelper/pathHelper.py
diseloryaHelper/pdfHelper.py
diseloryaHelper/stringHelper.py
diseloryaHelper/terminalHelper.py
diseloryahelper-0.0.0.3.dist-info/METADATA
diseloryahelper-0.0.0.3.dist-info/WHEEL
diseloryahelper-0.0.0.3.dist-info/licenses/LICENSE
diseloryahelper-0.0.0.3.dist-info/RECORD
