Metadata-Version: 2.1
Name: diseloryaHelper
Version: 0.0.0.3
Summary: Lc's python helper.
Project-URL: Homepage, https://github.com/Diselorya/LCsPythonHelper/
Author: Diselorya
License: Copyright (c) 2018 The Python Packaging Authority
License-File: LICENSE
Keywords: diselorya,lc-base-helper,python
Classifier: Development Status :: 3 - Alpha
Classifier: Intended Audience :: Developers
Classifier: Operating System :: Microsoft :: Windows
Classifier: Programming Language :: Python :: 3
Requires-Python: >=3.8
Requires-Dist: opencv-python
Requires-Dist: pangu
Requires-Dist: pypdf2
Requires-Dist: pytesseract
